rest_framework_rapidjson/__init__.py
rest_framework_rapidjson/parsers.py
rest_framework_rapidjson/renderers.py
djangorestframework_rapidjson-0.2.0.dist-info/LICENSE
djangorestframework_rapidjson-0.2.0.dist-info/METADATA
djangorestframework_rapidjson-0.2.0.dist-info/WHEEL
djangorestframework_rapidjson-0.2.0.dist-info/top_level.txt
djangorestframework_rapidjson-0.2.0.dist-info/RECORD
