Metadata-Version: 2.1
Name: djangorestframework-rapidjson
Version: 0.2.0
Summary: Provides rapidjson support with parser and renderer
Home-page: https://github.com/allisson/django-rest-framework-rapidjson
Author: Allisson Azevedo
Author-email: allisson@gmail.com
Keywords: djangorestframework rest json
Classifier: Development Status :: 5 - Production/Stable
Classifier: Environment :: Web Environment
Classifier: Intended Audience :: Developers
Classifier: License :: OSI Approved :: MIT License
Classifier: Operating System :: OS Independent
Classifier: Programming Language :: Python
Classifier: Programming Language :: Python :: 3.8
Classifier: Programming Language :: Python :: 3.9
Classifier: Programming Language :: Python :: 3.10
Classifier: Programming Language :: Python :: 3.11
Classifier: Programming Language :: Python :: 3.12
Classifier: Topic :: Internet :: WWW/HTTP
Classifier: Topic :: Software Development :: Libraries :: Application Frameworks
Classifier: Topic :: Software Development :: Libraries :: Python Modules
License-File: LICENSE
Requires-Dist: python-rapidjson >=1.12
Requires-Dist: djangorestframework >=3.12.4
